fdep/__init__.py
fdep/__main__.py
fdep/config.py
fdep/messages.py
fdep/runner.py
fdep/utils.py
fdep/backends/__init__.py
fdep/backends/gspreadsheet.py
fdep/backends/http.py
fdep/backends/s3.py
fdep/commands/__init__.py
fdep/commands/add.py
fdep/commands/commit.py
fdep/commands/freeze.py
fdep/commands/help.py
fdep/commands/init.py
fdep/commands/install.py
fdep/commands/link.py
fdep/commands/mv.py
fdep/commands/rm.py
fdep/commands/serve.py
fdep/commands/unfreeze.py
fdep/commands/upload.py
fdep/commands/version.py
fdep/interfaces/__init__.py
fdep/interfaces/progressbar.py
fdep/servers/__init__.py
fdep/servers/console.py
fdep/servers/jsonrpc.py
fdep/servers/xmlrpc.py
fdep/servers/integrations/__init__.py
fdep/servers/integrations/fluentd_http.py
fdep/servers/integrations/sentry.py
fdep-0.2.9.dist-info/LICENSE
fdep-0.2.9.dist-info/METADATA
fdep-0.2.9.dist-info/WHEEL
fdep-0.2.9.dist-info/entry_points.txt
fdep-0.2.9.dist-info/top_level.txt
fdep-0.2.9.dist-info/RECORD
