Metadata-Version: 2.1
Name: fdep
Version: 0.2.9
Summary: fdep is a framework-agnostic, transport-agnostic, extensible command line tool to shape workflows between machine learning experts and others.
Home-page: http://github.com/checkr/fdep
Author: Checkr
Author-email: eng@checkr.com
License: MIT LICENSE
Platform: UNKNOWN
Requires-Dist: PyYAML (>=3.12)
Requires-Dist: boto3 (>=1.4.4)
Requires-Dist: requests (>=2.11.1)
Requires-Dist: colorama (>=0.3.7)
Requires-Dist: tqdm (>=4.8.4)
Requires-Dist: json-rpc (>=1.10.3)
